{
    "openapi": "3.0.0",
    "info": {
        "title": "Icare Pet API",
        "description": "API para gerenciamento de clínicas de pet shop",
        "version": "1.0.0"
    },
    "servers": [
        {
            "url": "http://localhost:8081",
            "description": "Servidor principal"
        }
    ],
    "paths": {
        "/api/v1/administrador/login": {
            "post": {
                "tags": [
                    "Autenticação"
                ],
                "summary": "Login do administrador",
                "operationId": "b365e50b1043617749b87f6d270f68d5",
                "requestBody": {
                    "required": true,
                    "content": {
                        "application/json": {
                            "schema": {
                                "$ref": "#/components/schemas/LoginRequest"
                            }
                        }
                    }
                },
                "responses": {
                    "200": {
                        "description": "Login realizado com sucesso",
                        "content": {
                            "application/json": {
                                "schema": {
                                    "$ref": "#/components/schemas/LoginResponse"
                                }
                            }
                        }
                    },
                    "403": {
                        "description": "Credenciais inválidas"
                    },
                    "422": {
                        "description": "Erro de validação",
                        "content": {
                            "application/json": {
                                "schema": {
                                    "$ref": "#/components/schemas/ValidationError"
                                }
                            }
                        }
                    }
                }
            }
        },
        "/api/v1/administrador/logout": {
            "post": {
                "tags": [
                    "Autenticação"
                ],
                "summary": "Logout do administrador",
                "description": "Remove o token atual do usuário autenticado",
                "operationId": "56dd5c72381df1ab0c5e70ff96369373",
                "responses": {
                    "200": {
                        "description": "Logout realizado com sucesso",
                        "content": {
                            "application/json": {
                                "schema": {
                                    "$ref": "#/components/schemas/LogoutResponse"
                                }
                            }
                        }
                    },
                    "403": {
                        "description": "Usuário não autenticado ou token inválido"
                    }
                },
                "security": [
                    {
                        "bearerAuth": []
                    }
                ]
            }
        },
        "/api/v1/administrador/me": {
            "get": {
                "tags": [
                    "Autenticação"
                ],
                "summary": "Retorna os dados do administrador autenticado",
                "description": "Valida o token atual e retorna os dados do usuário autenticado",
                "operationId": "0b270e6107ca6a2f728d2a23a7d545ee",
                "responses": {
                    "200": {
                        "description": "Usuário autenticado com sucesso",
                        "content": {
                            "application/json": {
                                "schema": {
                                    "$ref": "#/components/schemas/LoginResponse"
                                }
                            }
                        }
                    },
                    "401": {
                        "description": "Não autenticado, token inválido ou expirado"
                    }
                },
                "security": [
                    {
                        "bearerAuth": []
                    }
                ]
            }
        },
        "/api/v1/administrador/gerar-pin": {
            "post": {
                "tags": [
                    "Autenticação"
                ],
                "summary": "Gera PIN para recuperação de senha",
                "description": "Gera um código PIN de 4 dígitos e envia por email para o usuário",
                "operationId": "237c15f38e2150b25462d9463b19b1f5",
                "requestBody": {
                    "required": true,
                    "content": {
                        "application/json": {
                            "schema": {
                                "$ref": "#/components/schemas/GerarPinRequest"
                            }
                        }
                    }
                },
                "responses": {
                    "200": {
                        "description": "PIN gerado e enviado com sucesso"
                    },
                    "400": {
                        "description": "Email não encontrado",
                        "content": {
                            "application/json": {
                                "schema": {
                                    "$ref": "#/components/schemas/BadRequestError"
                                }
                            }
                        }
                    },
                    "422": {
                        "description": "Erro de validação",
                        "content": {
                            "application/json": {
                                "schema": {
                                    "$ref": "#/components/schemas/ValidationError"
                                }
                            }
                        }
                    }
                }
            }
        },
        "/api/v1/administrador/validar-pin": {
            "post": {
                "tags": [
                    "Autenticação"
                ],
                "summary": "Valida PIN de recuperação de senha",
                "description": "Valida se o PIN informado é válido e não expirou",
                "operationId": "5bbdc30d84f16e78eedde65e2ed0c755",
                "requestBody": {
                    "required": true,
                    "content": {
                        "application/json": {
                            "schema": {
                                "$ref": "#/components/schemas/ValidarPinRequest"
                            }
                        }
                    }
                },
                "responses": {
                    "200": {
                        "description": "PIN válido",
                        "content": {
                            "application/json": {
                                "schema": {
                                    "$ref": "#/components/schemas/PinValidadoResponse"
                                }
                            }
                        }
                    },
                    "400": {
                        "description": "PIN inválido ou expirado",
                        "content": {
                            "application/json": {
                                "schema": {
                                    "$ref": "#/components/schemas/BadRequestError"
                                }
                            }
                        }
                    },
                    "422": {
                        "description": "Erro de validação",
                        "content": {
                            "application/json": {
                                "schema": {
                                    "$ref": "#/components/schemas/ValidationError"
                                }
                            }
                        }
                    }
                }
            }
        },
        "/api/v1/administrador/alterar-senha": {
            "post": {
                "tags": [
                    "Autenticação"
                ],
                "summary": "Altera a senha do usuário usando PIN",
                "description": "Valida o PIN e altera a senha do usuário",
                "operationId": "542991d91767ed78e3edeb99a71d96b5",
                "requestBody": {
                    "required": true,
                    "content": {
                        "application/json": {
                            "schema": {
                                "$ref": "#/components/schemas/AlterarSenhaRequest"
                            }
                        }
                    }
                },
                "responses": {
                    "200": {
                        "description": "Senha alterada com sucesso",
                        "content": {
                            "application/json": {
                                "schema": {
                                    "$ref": "#/components/schemas/SenhaAlteradaSchema"
                                }
                            }
                        }
                    },
                    "400": {
                        "description": "PIN inválido",
                        "content": {
                            "application/json": {
                                "schema": {
                                    "$ref": "#/components/schemas/BadRequestError"
                                }
                            }
                        }
                    },
                    "404": {
                        "description": "Usuário não encontrado"
                    },
                    "422": {
                        "description": "Erro de validação",
                        "content": {
                            "application/json": {
                                "schema": {
                                    "$ref": "#/components/schemas/ValidationError"
                                }
                            }
                        }
                    }
                }
            }
        },
        "/api/v1/cliente": {
            "get": {
                "tags": [
                    "Cliente"
                ],
                "summary": "Lista clientes com filtros e paginação",
                "operationId": "3974b5b9a0a0e69c065617e466e823ab",
                "parameters": [
                    {
                        "name": "nome",
                        "in": "query",
                        "schema": {
                            "type": "string"
                        }
                    },
                    {
                        "name": "documento",
                        "in": "query",
                        "schema": {
                            "type": "string"
                        }
                    },
                    {
                        "name": "email",
                        "in": "query",
                        "schema": {
                            "type": "string"
                        }
                    },
                    {
                        "name": "data_nascimento[inicio]",
                        "in": "query",
                        "schema": {
                            "type": "string",
                            "format": "date"
                        }
                    },
                    {
                        "name": "data_nascimento[fim]",
                        "in": "query",
                        "schema": {
                            "type": "string",
                            "format": "date"
                        }
                    },
                    {
                        "name": "limite",
                        "in": "query",
                        "schema": {
                            "type": "integer",
                            "example": 15
                        }
                    }
                ],
                "responses": {
                    "200": {
                        "description": "Lista paginada de clientes",
                        "content": {
                            "application/json": {
                                "schema": {
                                    "$ref": "#/components/schemas/BasePaginatedResponse"
                                }
                            }
                        }
                    },
                    "401": {
                        "description": "Não autenticado"
                    }
                },
                "security": [
                    {
                        "bearerAuth": []
                    }
                ]
            },
            "post": {
                "tags": [
                    "Cliente"
                ],
                "summary": "Cadastrar novo cliente",
                "operationId": "629991b54b57b531321bb5c725aed199",
                "requestBody": {
                    "description": "Dados para criação do cliente",
                    "required": true,
                    "content": {
                        "application/json": {
                            "schema": {
                                "$ref": "#/components/schemas/ClienteStoreRequest"
                            }
                        }
                    }
                },
                "responses": {
                    "201": {
                        "description": "Cliente criado com sucesso",
                        "content": {
                            "application/json": {
                                "schema": {
                                    "$ref": "#/components/schemas/Cliente"
                                }
                            }
                        }
                    },
                    "422": {
                        "description": "Erro de validação"
                    },
                    "401": {
                        "description": "Não autenticado"
                    }
                },
                "security": [
                    {
                        "bearerAuth": []
                    }
                ]
            }
        },
        "/api/v1/cliente/{id}": {
            "get": {
                "tags": [
                    "Cliente"
                ],
                "summary": "Busca cliente por ID",
                "operationId": "35eae00678cdd5da60cb4c2fc3c5b179",
                "parameters": [
                    {
                        "name": "id",
                        "in": "path",
                        "required": true,
                        "schema": {
                            "type": "integer"
                        }
                    }
                ],
                "responses": {
                    "200": {
                        "description": "Cliente encontrado",
                        "content": {
                            "application/json": {
                                "schema": {
                                    "$ref": "#/components/schemas/Cliente"
                                }
                            }
                        }
                    },
                    "404": {
                        "description": "Cliente não encontrado"
                    },
                    "401": {
                        "description": "Não autenticado"
                    }
                },
                "security": [
                    {
                        "bearerAuth": []
                    }
                ]
            },
            "put": {
                "tags": [
                    "Cliente"
                ],
                "summary": "Atualizar cliente",
                "operationId": "f4c28ed0242f84aeb90c0fd05728f614",
                "parameters": [
                    {
                        "name": "id",
                        "in": "path",
                        "description": "ID do cliente",
                        "required": true,
                        "schema": {
                            "type": "integer"
                        }
                    }
                ],
                "requestBody": {
                    "required": true,
                    "content": {
                        "application/json": {
                            "schema": {
                                "$ref": "#/components/schemas/ClienteUpdateRequest"
                            }
                        }
                    }
                },
                "responses": {
                    "200": {
                        "description": "Cliente atualizado com sucesso",
                        "content": {
                            "application/json": {
                                "schema": {
                                    "$ref": "#/components/schemas/Cliente"
                                }
                            }
                        }
                    },
                    "404": {
                        "description": "Cliente não encontrado"
                    },
                    "422": {
                        "description": "Erro de validação"
                    },
                    "401": {
                        "description": "Não autenticado"
                    }
                },
                "security": [
                    {
                        "bearerAuth": []
                    }
                ]
            },
            "delete": {
                "tags": [
                    "Cliente"
                ],
                "summary": "Remover cliente",
                "operationId": "e052e516e3f4c98e4651c011907e1907",
                "parameters": [
                    {
                        "name": "id",
                        "in": "path",
                        "required": true,
                        "schema": {
                            "type": "integer"
                        }
                    }
                ],
                "responses": {
                    "204": {
                        "description": "Cliente removido com sucesso"
                    },
                    "404": {
                        "description": "Cliente não encontrado"
                    },
                    "401": {
                        "description": "Não autenticado"
                    }
                },
                "security": [
                    {
                        "bearerAuth": []
                    }
                ]
            }
        },
        "/api/v1/pet": {
            "get": {
                "tags": [
                    "Pet"
                ],
                "summary": "Listar pets com filtros e paginação",
                "operationId": "9e260e234db7b4bd1e8dd0f4574073ac",
                "parameters": [
                    {
                        "name": "nome",
                        "in": "query",
                        "schema": {
                            "type": "string"
                        }
                    },
                    {
                        "name": "documento",
                        "in": "query",
                        "schema": {
                            "type": "string"
                        }
                    },
                    {
                        "name": "data_nascimento[inicio]",
                        "in": "query",
                        "schema": {
                            "type": "string",
                            "format": "date"
                        }
                    },
                    {
                        "name": "data_nascimento[fim]",
                        "in": "query",
                        "schema": {
                            "type": "string",
                            "format": "date"
                        }
                    },
                    {
                        "name": "tamanho",
                        "in": "query",
                        "schema": {
                            "type": "string"
                        }
                    },
                    {
                        "name": "cor",
                        "in": "query",
                        "schema": {
                            "type": "string"
                        }
                    },
                    {
                        "name": "numero_microship",
                        "in": "query",
                        "schema": {
                            "type": "string"
                        }
                    },
                    {
                        "name": "cliente.nome",
                        "in": "query",
                        "schema": {
                            "type": "string"
                        }
                    },
                    {
                        "name": "cliente.documento",
                        "in": "query",
                        "schema": {
                            "type": "string"
                        }
                    },
                    {
                        "name": "per_page",
                        "in": "query",
                        "schema": {
                            "type": "integer",
                            "example": 15
                        }
                    },
                    {
                        "name": "page",
                        "in": "query",
                        "schema": {
                            "type": "integer",
                            "example": 1
                        }
                    }
                ],
                "responses": {
                    "200": {
                        "description": "Lista paginada de pets",
                        "content": {
                            "application/json": {
                                "schema": {
                                    "allOf": [
                                        {
                                            "$ref": "#/components/schemas/PaginatedResponse"
                                        },
                                        {
                                            "properties": {
                                                "data": {
                                                    "type": "array",
                                                    "items": {
                                                        "$ref": "#/components/schemas/Pet"
                                                    }
                                                }
                                            },
                                            "type": "object"
                                        }
                                    ]
                                }
                            }
                        }
                    },
                    "401": {
                        "description": "Não autenticado"
                    }
                },
                "security": [
                    {
                        "bearerAuth": []
                    }
                ]
            }
        },
        "/api/v1/cliente/{cliente}/pet": {
            "post": {
                "tags": [
                    "Pet"
                ],
                "summary": "Cadastrar pet para um cliente",
                "description": "Cria um novo pet vinculado a um cliente existente.",
                "operationId": "cc831ad2138fb02c8af138e01ca32e49",
                "parameters": [
                    {
                        "name": "cliente",
                        "in": "path",
                        "description": "ID do cliente",
                        "required": true,
                        "schema": {
                            "type": "integer",
                            "example": 10
                        }
                    }
                ],
                "requestBody": {
                    "description": "Dados necessários para cadastro do pet",
                    "required": true,
                    "content": {
                        "application/json": {
                            "schema": {
                                "required": [
                                    "nome",
                                    "documento",
                                    "tamanho",
                                    "cor",
                                    "especie_id"
                                ],
                                "properties": {
                                    "nome": {
                                        "type": "string",
                                        "maxLength": 255,
                                        "example": "Rex"
                                    },
                                    "documento": {
                                        "type": "string",
                                        "maxLength": 255,
                                        "example": "PET-001"
                                    },
                                    "tamanho": {
                                        "description": "Enum PetTamanhoEnum",
                                        "type": "string",
                                        "enum": [
                                            "PEQUENO",
                                            "MEDIO",
                                            "GRANDE"
                                        ],
                                        "example": "MEDIO"
                                    },
                                    "cor": {
                                        "type": "string",
                                        "example": "Caramelo"
                                    },
                                    "tem_microship": {
                                        "description": "Indica se o pet possui microchip",
                                        "type": "boolean",
                                        "example": true,
                                        "nullable": true
                                    },
                                    "numero_microship": {
                                        "description": "Obrigatório quando tem_microship = true",
                                        "type": "string",
                                        "example": "123456789ABC",
                                        "nullable": true
                                    },
                                    "especie_id": {
                                        "description": "ID existente na tabela especies",
                                        "type": "integer",
                                        "example": 2
                                    }
                                },
                                "type": "object"
                            }
                        }
                    }
                },
                "responses": {
                    "201": {
                        "description": "Pet criado com sucesso",
                        "content": {
                            "application/json": {
                                "schema": {
                                    "properties": {
                                        "id": {
                                            "type": "integer",
                                            "example": 15
                                        },
                                        "nome": {
                                            "type": "string",
                                            "example": "Rex"
                                        },
                                        "documento": {
                                            "type": "string",
                                            "example": "PET-001"
                                        },
                                        "tamanho": {
                                            "type": "string",
                                            "enum": [
                                                "PEQUENO",
                                                "MEDIO",
                                                "GRANDE"
                                            ],
                                            "example": "MEDIO"
                                        },
                                        "cor": {
                                            "type": "string",
                                            "example": "Caramelo"
                                        },
                                        "tem_microship": {
                                            "type": "boolean",
                                            "example": true
                                        },
                                        "numero_microship": {
                                            "type": "string",
                                            "example": "123456789ABC"
                                        },
                                        "especie_id": {
                                            "type": "integer",
                                            "example": 2
                                        },
                                        "created_at": {
                                            "type": "string",
                                            "format": "date-time"
                                        },
                                        "updated_at": {
                                            "type": "string",
                                            "format": "date-time"
                                        }
                                    },
                                    "type": "object"
                                }
                            }
                        }
                    },
                    "401": {
                        "description": "Não autenticado"
                    },
                    "404": {
                        "description": "Cliente não encontrado"
                    },
                    "422": {
                        "description": "Erro de validação"
                    }
                },
                "security": [
                    {
                        "bearerAuth": []
                    }
                ]
            }
        },
        "/api/v1/pet/{id}": {
            "get": {
                "tags": [
                    "Pet"
                ],
                "summary": "Buscar pet por ID",
                "description": "Retorna os dados de um pet específico.",
                "operationId": "4fc18e031853ad806240436abdbebfef",
                "parameters": [
                    {
                        "name": "id",
                        "in": "path",
                        "description": "ID do pet",
                        "required": true,
                        "schema": {
                            "type": "integer",
                            "example": 15
                        }
                    }
                ],
                "responses": {
                    "200": {
                        "description": "Pet encontrado com sucesso",
                        "content": {
                            "application/json": {
                                "schema": {
                                    "$ref": "#/components/schemas/Pet"
                                }
                            }
                        }
                    },
                    "401": {
                        "description": "Não autenticado"
                    },
                    "404": {
                        "description": "Pet não encontrado"
                    }
                },
                "security": [
                    {
                        "bearerAuth": []
                    }
                ]
            },
            "put": {
                "tags": [
                    "Pet"
                ],
                "summary": "Atualizar pet",
                "description": "Atualiza os dados de um pet existente.",
                "operationId": "22cb2c984b9fe3819727686595d74057",
                "parameters": [
                    {
                        "name": "id",
                        "in": "path",
                        "description": "ID do pet",
                        "required": true,
                        "schema": {
                            "type": "integer",
                            "example": 15
                        }
                    }
                ],
                "requestBody": {
                    "required": true,
                    "content": {
                        "application/json": {
                            "schema": {
                                "$ref": "#/components/schemas/PetUpdateRequest"
                            }
                        }
                    }
                },
                "responses": {
                    "200": {
                        "description": "Pet atualizado com sucesso",
                        "content": {
                            "application/json": {
                                "schema": {
                                    "$ref": "#/components/schemas/Pet"
                                }
                            }
                        }
                    },
                    "401": {
                        "description": "Não autenticado"
                    },
                    "404": {
                        "description": "Pet não encontrado"
                    },
                    "422": {
                        "description": "Erro de validação"
                    }
                },
                "security": [
                    {
                        "bearerAuth": []
                    }
                ]
            },
            "delete": {
                "tags": [
                    "Pet"
                ],
                "summary": "Remover pet",
                "description": "Remove um pet existente.",
                "operationId": "69b2bdeb0e6d229cb65b41f8d6512684",
                "parameters": [
                    {
                        "name": "id",
                        "in": "path",
                        "description": "ID do pet",
                        "required": true,
                        "schema": {
                            "type": "integer",
                            "example": 15
                        }
                    }
                ],
                "responses": {
                    "200": {
                        "description": "Pet removido com sucesso",
                        "content": {
                            "application/json": {
                                "schema": {
                                    "$ref": "#/components/schemas/Pet"
                                }
                            }
                        }
                    },
                    "401": {
                        "description": "Não autenticado"
                    },
                    "404": {
                        "description": "Pet não encontrado"
                    }
                },
                "security": [
                    {
                        "bearerAuth": []
                    }
                ]
            }
        }
    },
    "components": {
        "schemas": {
            "AlterarSenhaRequest": {
                "required": [
                    "email",
                    "pin",
                    "senha",
                    "senha_confirmation"
                ],
                "properties": {
                    "email": {
                        "type": "string",
                        "format": "email",
                        "example": "admin@email.com"
                    },
                    "pin": {
                        "description": "PIN enviado por email",
                        "type": "string",
                        "example": "123456"
                    },
                    "senha": {
                        "type": "string",
                        "format": "password",
                        "minLength": 6,
                        "example": "novasenha123"
                    },
                    "senha_confirmation": {
                        "type": "string",
                        "format": "password",
                        "example": "novasenha123"
                    }
                },
                "type": "object"
            },
            "ClienteStoreRequest": {
                "required": [
                    "nome",
                    "email",
                    "documento",
                    "endereco"
                ],
                "properties": {
                    "nome": {
                        "type": "string",
                        "maxLength": 255,
                        "example": "João Silva"
                    },
                    "email": {
                        "type": "string",
                        "format": "email",
                        "example": "joao@email.com"
                    },
                    "documento": {
                        "type": "string",
                        "maxLength": 11,
                        "example": "12345678900"
                    },
                    "data_nascimento": {
                        "type": "string",
                        "format": "date",
                        "example": "1990-01-01",
                        "nullable": true
                    },
                    "endereco": {
                        "$ref": "#/components/schemas/Endereco"
                    },
                    "contatos": {
                        "type": "array",
                        "items": {
                            "$ref": "#/components/schemas/Contato"
                        },
                        "nullable": true
                    }
                },
                "type": "object"
            },
            "ClienteUpdateRequest": {
                "required": [
                    "nome",
                    "email",
                    "documento"
                ],
                "properties": {
                    "nome": {
                        "type": "string",
                        "example": "João Atualizado"
                    },
                    "email": {
                        "type": "string",
                        "format": "email",
                        "example": "joao@email.com"
                    },
                    "documento": {
                        "type": "string",
                        "example": "12345678900"
                    }
                },
                "type": "object"
            },
            "GerarPinRequest": {
                "required": [
                    "email"
                ],
                "properties": {
                    "email": {
                        "type": "string",
                        "format": "email",
                        "example": "admin@email.com"
                    }
                },
                "type": "object"
            },
            "LoginRequest": {
                "required": [
                    "email",
                    "senha"
                ],
                "properties": {
                    "email": {
                        "type": "string",
                        "format": "email",
                        "example": "admin@email.com"
                    },
                    "senha": {
                        "type": "string",
                        "format": "password",
                        "example": "123456"
                    }
                },
                "type": "object"
            },
            "PetStoreRequest": {
                "required": [
                    "nome",
                    "documento",
                    "tamanho",
                    "cor",
                    "especie_id"
                ],
                "properties": {
                    "nome": {
                        "type": "string",
                        "maxLength": 255,
                        "example": "Rex"
                    },
                    "documento": {
                        "type": "string",
                        "maxLength": 255,
                        "example": "PET-001"
                    },
                    "tamanho": {
                        "description": "Enum PetTamanhoEnum",
                        "type": "string",
                        "enum": [
                            "PEQUENO",
                            "MEDIO",
                            "GRANDE"
                        ],
                        "example": "MEDIO"
                    },
                    "cor": {
                        "type": "string",
                        "example": "Caramelo"
                    },
                    "tem_microship": {
                        "description": "Indica se o pet possui microchip",
                        "type": "boolean",
                        "example": true,
                        "nullable": true
                    },
                    "numero_microship": {
                        "description": "Obrigatório quando tem_microship = true",
                        "type": "string",
                        "example": "123456789ABC",
                        "nullable": true
                    },
                    "especie_id": {
                        "description": "ID da espécie cadastrada",
                        "type": "integer",
                        "example": 2
                    }
                },
                "type": "object"
            },
            "PetUpdateRequest": {
                "required": [
                    "nome",
                    "documento",
                    "tamanho",
                    "cor",
                    "especie_id"
                ],
                "properties": {
                    "nome": {
                        "type": "string",
                        "maxLength": 255,
                        "example": "Rex"
                    },
                    "documento": {
                        "type": "string",
                        "maxLength": 255,
                        "example": "PET-002"
                    },
                    "tamanho": {
                        "type": "string",
                        "enum": [
                            "PEQUENO",
                            "MEDIO",
                            "GRANDE"
                        ],
                        "example": "GRANDE"
                    },
                    "cor": {
                        "type": "string",
                        "example": "Preto"
                    },
                    "ativo": {
                        "description": "Indica se o pet está ativo",
                        "type": "boolean",
                        "example": true,
                        "nullable": true
                    },
                    "tem_microship": {
                        "type": "boolean",
                        "example": true,
                        "nullable": true
                    },
                    "numero_microship": {
                        "type": "string",
                        "example": "ABC123456",
                        "nullable": true
                    },
                    "especie_id": {
                        "type": "integer",
                        "example": 2
                    }
                },
                "type": "object"
            },
            "ValidarPinRequest": {
                "required": [
                    "email",
                    "pin"
                ],
                "properties": {
                    "email": {
                        "type": "string",
                        "format": "email",
                        "example": "admin@email.com"
                    },
                    "pin": {
                        "description": "PIN de 4 dígitos enviado por email",
                        "type": "string",
                        "example": "1234"
                    }
                },
                "type": "object"
            },
            "BadRequestError": {
                "properties": {
                    "message": {
                        "type": "string",
                        "example": "Email informado não foi encontrado!"
                    }
                },
                "type": "object"
            },
            "BasePaginatedResponse": {
                "allOf": [
                    {
                        "$ref": "#/components/schemas/PaginatedResponse "
                    },
                    {
                        "properties": {
                            "data": {
                                "type": "array",
                                "items": {
                                    "$ref": "#/components/schemas/Cliente"
                                }
                            }
                        },
                        "type": "object"
                    }
                ]
            },
            "LoginResponse": {
                "properties": {
                    "usuario": {
                        "$ref": "#/components/schemas/Usuario"
                    },
                    "token": {
                        "type": "string",
                        "example": "1|asdhjkasdhjkashdkjashdkjashdk"
                    }
                },
                "type": "object"
            },
            "LogoutResponse": {
                "properties": {
                    "usuario": {
                        "$ref": "#/components/schemas/Usuario"
                    },
                    "token": {
                        "type": "string",
                        "example": "admin-token",
                        "nullable": true
                    }
                },
                "type": "object"
            },
            "PaginatedResponse ": {
                "properties": {
                    "links": {
                        "properties": {
                            "first": {
                                "type": "string",
                                "nullable": true
                            },
                            "last": {
                                "type": "string",
                                "nullable": true
                            },
                            "prev": {
                                "type": "string",
                                "nullable": true
                            },
                            "next": {
                                "type": "string",
                                "nullable": true
                            }
                        },
                        "type": "object"
                    },
                    "meta": {
                        "properties": {
                            "current_page": {
                                "type": "integer"
                            },
                            "from": {
                                "type": "integer",
                                "nullable": true
                            },
                            "last_page": {
                                "type": "integer"
                            },
                            "path": {
                                "type": "string"
                            },
                            "per_page": {
                                "type": "integer"
                            },
                            "to": {
                                "type": "integer",
                                "nullable": true
                            },
                            "total": {
                                "type": "integer"
                            }
                        },
                        "type": "object"
                    }
                },
                "type": "object"
            },
            "PinValidadoResponse": {
                "properties": {
                    "message": {
                        "type": "string",
                        "example": "PIN válido."
                    }
                },
                "type": "object"
            },
            "SenhaAlteradaSchema": {
                "properties": {
                    "message": {
                        "type": "string",
                        "example": "Senha alterada com sucesso."
                    }
                },
                "type": "object"
            },
            "ValidationError": {
                "properties": {
                    "message": {
                        "type": "string",
                        "example": "O campo email é obrigatório."
                    },
                    "errors": {
                        "type": "object",
                        "additionalProperties": {
                            "type": "array",
                            "items": {
                                "type": "string"
                            }
                        }
                    }
                },
                "type": "object"
            },
            "Cliente": {
                "properties": {
                    "id": {
                        "type": "integer",
                        "example": 10
                    },
                    "nome": {
                        "type": "string",
                        "example": "João Silva"
                    },
                    "email": {
                        "type": "string",
                        "format": "email",
                        "example": "joao@email.com"
                    },
                    "documento": {
                        "type": "string",
                        "example": "12345678900"
                    },
                    "data_nascimento": {
                        "type": "string",
                        "format": "date",
                        "example": "1990-01-01",
                        "nullable": true
                    },
                    "endereco": {
                        "oneOf": [
                            {
                                "$ref": "#/components/schemas/Endereco"
                            }
                        ],
                        "nullable": true
                    },
                    "contatos": {
                        "type": "array",
                        "items": {
                            "$ref": "#/components/schemas/ContatoResponse"
                        },
                        "nullable": true
                    }
                },
                "type": "object"
            },
            "ContatoResponse": {
                "properties": {
                    "id": {
                        "type": "integer",
                        "example": 1
                    },
                    "tipo": {
                        "type": "string",
                        "example": "telefone"
                    },
                    "valor": {
                        "type": "string",
                        "example": "(11)99999-9999"
                    }
                },
                "type": "object"
            },
            "Contato": {
                "required": [
                    "nome",
                    "tipo",
                    "valor"
                ],
                "properties": {
                    "nome": {
                        "type": "string",
                        "example": "João da Silva"
                    },
                    "tipo": {
                        "type": "string",
                        "example": "TELEFONE"
                    },
                    "valor": {
                        "type": "string",
                        "example": "(11)99999-9999"
                    },
                    "preferencial": {
                        "type": "boolean",
                        "example": true
                    }
                },
                "type": "object"
            },
            "Endereco": {
                "required": [
                    "cep",
                    "logradouro",
                    "numero",
                    "bairro",
                    "cidade"
                ],
                "properties": {
                    "cep": {
                        "type": "string",
                        "example": "01001000"
                    },
                    "logradouro": {
                        "type": "string",
                        "example": "Rua das Flores"
                    },
                    "numero": {
                        "type": "integer",
                        "example": 123
                    },
                    "complemento": {
                        "type": "string",
                        "example": "Apto 12",
                        "nullable": true
                    },
                    "bairro": {
                        "type": "string",
                        "example": "Centro"
                    },
                    "cidade": {
                        "type": "string",
                        "example": "São Paulo"
                    }
                },
                "type": "object"
            },
            "PaginatedResponse": {
                "properties": {
                    "current_page": {
                        "type": "integer",
                        "example": 1
                    },
                    "data": {
                        "type": "array",
                        "items": {}
                    },
                    "first_page_url": {
                        "type": "string",
                        "example": "http://api.test/api/v1/administrador/pet?page=1"
                    },
                    "from": {
                        "type": "integer",
                        "example": 1,
                        "nullable": true
                    },
                    "last_page": {
                        "type": "integer",
                        "example": 10
                    },
                    "last_page_url": {
                        "type": "string"
                    },
                    "links": {
                        "type": "array",
                        "items": {
                            "properties": {
                                "url": {
                                    "type": "string",
                                    "nullable": true
                                },
                                "label": {
                                    "type": "string"
                                },
                                "active": {
                                    "type": "boolean"
                                }
                            },
                            "type": "object"
                        }
                    },
                    "next_page_url": {
                        "type": "string",
                        "nullable": true
                    },
                    "path": {
                        "type": "string"
                    },
                    "per_page": {
                        "type": "integer",
                        "example": 15
                    },
                    "prev_page_url": {
                        "type": "string",
                        "nullable": true
                    },
                    "to": {
                        "type": "integer",
                        "example": 15,
                        "nullable": true
                    },
                    "total": {
                        "type": "integer",
                        "example": 150
                    }
                },
                "type": "object"
            },
            "Pet": {
                "properties": {
                    "id": {
                        "type": "integer",
                        "example": 15
                    },
                    "nome": {
                        "type": "string",
                        "example": "Rex"
                    },
                    "documento": {
                        "type": "string",
                        "example": "PET-001"
                    },
                    "cor": {
                        "type": "string",
                        "example": "Caramelo"
                    },
                    "tamanho": {
                        "type": "string",
                        "enum": [
                            "PEQUENO",
                            "MEDIO",
                            "GRANDE"
                        ],
                        "example": "MEDIO"
                    },
                    "numero_microship": {
                        "type": "string",
                        "example": "123456789ABC",
                        "nullable": true
                    },
                    "created_at": {
                        "type": "string",
                        "format": "date-time",
                        "example": "2026-02-22T10:30:00Z"
                    },
                    "updated_at": {
                        "type": "string",
                        "format": "date-time",
                        "example": "2026-02-22T10:30:00Z"
                    }
                },
                "type": "object"
            },
            "Usuario": {
                "properties": {
                    "id": {
                        "type": "integer",
                        "example": 1
                    },
                    "nome": {
                        "type": "string",
                        "example": "Administrador"
                    },
                    "email": {
                        "type": "string",
                        "example": "admin@email.com"
                    }
                },
                "type": "object"
            }
        },
        "securitySchemes": {
            "bearerAuth": {
                "type": "http",
                "bearerFormat": "JWT",
                "scheme": "bearer"
            }
        }
    },
    "tags": [
        {
            "name": "Autenticação",
            "description": "Autenticação"
        },
        {
            "name": "Cliente",
            "description": "Cliente"
        },
        {
            "name": "Pet",
            "description": "Pet"
        }
    ]
}